ylib/core.py
ylib/time_struct.py
ylib/ymath.py
ylib-0.1.0.dist-info/WHEEL
ylib-0.1.0.dist-info/METADATA
ylib-0.1.0.dist-info/RECORD
